<INVENTORY_ADJUST_IFD>
	<ADJ_SEG>
		<TRANID>INV-ADJ</TRANID>
		<SITCOD>14</SITCOD>
		<TRNNUM>20251030161016</TRNNUM>
		<PRTNUM>0401500</PRTNUM>
		<PRT_CLIENT_ID>----</PRT_CLIENT_ID>
		<ORGCOD></ORGCOD>
		<REVLVL></REVLVL>
		<LOTNUM></LOTNUM>
		<ADJQTY>-000000017</ADJQTY>
		<REACOD>T</REACOD>
		<STKUOM>EA</STKUOM>
		<CATCH_UNTTYP>pound</CATCH_UNTTYP>
		<CATCH_QTY> 0.00</CATCH_QTY>
		<ADJ_REF1>140106693</ADJ_REF1>
		<ADJ_REF2>PERM-ADJ-LOC</ADJ_REF2>
		<WH_ID>WMD1</WH_ID>
		<TRNDTE>20251030161016</TRNDTE>
	</ADJ_SEG>
</INVENTORY_ADJUST_IFD>